investigate/__init__.py
investigate/investigate.py
investigate-1.10.1.dist-info/LICENSE
investigate-1.10.1.dist-info/METADATA
investigate-1.10.1.dist-info/WHEEL
investigate-1.10.1.dist-info/top_level.txt
investigate-1.10.1.dist-info/RECORD
