Metadata-Version: 2.1
Name: investigate
Version: 1.10.1
Summary: Python interface for the OpenDNS Investigate API
Home-page: https://github.com/opendns/pyinvestigate
Author: Skyler Hawthorne, Thibault Reuille
Author-email: skylerhawthorne@gmail.com, thibault@opendns.com
License: MIT
Keywords: opendns investigate
Platform: UNKNOWN
Requires-Dist: requests
Requires-Dist: future
